{
    "parent": "minecraft:recipes/root",
    "rewards": {
        "recipes": [
            "unpacking:sandstone_to_sand"
        ]
    },
    "criteria": {
        "has_sandstone": {
            "trigger": "minecraft:inventory_changed",
            "conditions": {
                "items": [
                    {
                        "item": "minecraft:sandstone"
                    }
                ]
            }
        }
    },
    "requirements": [
        [
            "has_sandstone"
        ]
    ]
}